HeliumBot-0.1.2.dist-info/METADATA
HeliumBot-0.1.2.dist-info/RECORD
HeliumBot-0.1.2.dist-info/WHEEL
HeliumBot-0.1.2.dist-info/top_level.txt
heliumbot/plugins/pyworld.py
